Metadata-Version: 2.1
Name: pgadmin4-desktop-mode
Version: 0.0.1
Summary: Run pgdamin4 in desktop mode
Home-page: https://github.com/science-computing/pgadmin4-desktop-mode
Author: Anselm Kruis
Author-email: anselm.kruis@atos.net
License: UNKNOWN
Project-URL: Bug Tracker, https://github.com/science-computing/pgadmin4-desktop-mode/issues
Platform: UNKNOWN
Classifier: Programming Language :: Python :: 3
Classifier: License :: OSI Approved :: PostgreSQL License
Classifier: Operating System :: OS Independent
Classifier: Topic :: Database :: Front-Ends
Requires-Python: >=3.6.0
License-File: LICENSE
